oh_my_stars-1.5.1.dist-info/DESCRIPTION.rst
oh_my_stars-1.5.1.dist-info/METADATA
oh_my_stars-1.5.1.dist-info/RECORD
oh_my_stars-1.5.1.dist-info/WHEEL
oh_my_stars-1.5.1.dist-info/entry_points.txt
oh_my_stars-1.5.1.dist-info/metadata.json
oh_my_stars-1.5.1.dist-info/top_level.txt
ohmystars/__init__.py
ohmystars/__main__.py
ohmystars/core.py
ohmystars/db.py
ohmystars/index.py
ohmystars/tests.py
ohmystars/view.py
