Metadata-Version: 2.0
Name: oh-my-stars
Version: 1.5.1
Summary: a CLI tool to search your GitHub stars.
Home-page: https://github.com/wolfg1969/oh-my-stars
Author: wolfg1969
Author-email: wolfg1969@gmail.com
License: MIT
Keywords: github command tools
Platform: any
Classifier: Development Status :: 2 - Pre-Alpha
Classifier: Intended Audience :: Developers
Classifier: License :: OSI Approved :: MIT License
Classifier: Programming Language :: Python
Classifier: Operating System :: OS Independent
Classifier: Environment :: Console
Classifier: Programming Language :: Python :: 2
Classifier: Programming Language :: Python :: 2.7
Classifier: Programming Language :: Python :: 3
Classifier: Programming Language :: Python :: 3.3
Classifier: Programming Language :: Python :: 3.4
Classifier: Programming Language :: Python :: 3.5
Classifier: Programming Language :: Python :: 3.6
Classifier: Topic :: Terminals
Classifier: Topic :: Utilities
Requires-Dist: colorama (==0.3.9)
Requires-Dist: future (==0.16.0)
Requires-Dist: github3.py (==0.9.6)
Requires-Dist: tinydb (==3.7.0)
Requires-Dist: ujson (==1.35)
Requires-Dist: argparse (>=1.2.1); python_version == "3.0" or python_version == "3.1"
Requires-Dist: pyreadline; sys_platform == "win32"
